{
  "updated_at": "2026-05-21T18:17:38.828085+00:00",
  "total_bets": 857,
  "wins": 517,
  "losses": 340,
  "pending": 0,
  "win_rate": 60.3,
  "pnl": -24.09,
  "kelly_pnl": -34.04,
  "current_streak": 3,
  "streak_type": "L",
  "daily": [
    {
      "date": "2026-05-21",
      "bets": 123,
      "wins": 71,
      "losses": 52,
      "wr": 57.7
    },
    {
      "date": "2026-05-20",
      "bets": 130,
      "wins": 71,
      "losses": 59,
      "wr": 54.6
    },
    {
      "date": "2026-05-19",
      "bets": 142,
      "wins": 88,
      "losses": 54,
      "wr": 62.0
    },
    {
      "date": "2026-05-18",
      "bets": 129,
      "wins": 74,
      "losses": 55,
      "wr": 57.4
    },
    {
      "date": "2026-05-17",
      "bets": 109,
      "wins": 66,
      "losses": 43,
      "wr": 60.6
    },
    {
      "date": "2026-05-16",
      "bets": 78,
      "wins": 50,
      "losses": 28,
      "wr": 64.1
    },
    {
      "date": "2026-05-15",
      "bets": 131,
      "wins": 86,
      "losses": 45,
      "wr": 65.6
    },
    {
      "date": "2026-05-14",
      "bets": 15,
      "wins": 11,
      "losses": 4,
      "wr": 73.3
    }
  ],
  "recent_signals": [
    {
      "timestamp": "2026-05-21T18:00:12.295027+00:00",
      "coin": "ETH",
      "direction": "UP",
      "entry_price": 0.62,
      "secs": 12.2,
      "outcome": "LOSS",
      "slug": "eth-updown-5m-1779386400"
    },
    {
      "timestamp": "2026-05-21T17:55:12.108541+00:00",
      "coin": "BTC",
      "direction": "UP",
      "entry_price": 0.63,
      "secs": 12.0,
      "outcome": "LOSS",
      "slug": "btc-updown-5m-1779386100"
    },
    {
      "timestamp": "2026-05-21T17:55:05.942823+00:00",
      "coin": "ETH",
      "direction": "UP",
      "entry_price": 0.58,
      "secs": 5.9,
      "outcome": "LOSS",
      "slug": "eth-updown-5m-1779386100"
    },
    {
      "timestamp": "2026-05-21T17:45:23.980917+00:00",
      "coin": "BTC",
      "direction": "UP",
      "entry_price": 0.6,
      "secs": 23.9,
      "outcome": "WIN",
      "slug": "btc-updown-5m-1779385500"
    },
    {
      "timestamp": "2026-05-21T17:40:18.438333+00:00",
      "coin": "ETH",
      "direction": "UP",
      "entry_price": 0.63,
      "secs": 18.4,
      "outcome": "WIN",
      "slug": "eth-updown-5m-1779385200"
    },
    {
      "timestamp": "2026-05-21T17:40:14.426973+00:00",
      "coin": "BTC",
      "direction": "UP",
      "entry_price": 0.58,
      "secs": 14.4,
      "outcome": "LOSS",
      "slug": "btc-updown-5m-1779385200"
    },
    {
      "timestamp": "2026-05-21T17:35:19.833274+00:00",
      "coin": "ETH",
      "direction": "UP",
      "entry_price": 0.64,
      "secs": 19.8,
      "outcome": "LOSS",
      "slug": "eth-updown-5m-1779384900"
    },
    {
      "timestamp": "2026-05-21T17:25:14.163812+00:00",
      "coin": "ETH",
      "direction": "UP",
      "entry_price": 0.6,
      "secs": 14.1,
      "outcome": "WIN",
      "slug": "eth-updown-5m-1779384300"
    },
    {
      "timestamp": "2026-05-21T17:25:12.109571+00:00",
      "coin": "BTC",
      "direction": "UP",
      "entry_price": 0.6,
      "secs": 12.0,
      "outcome": "WIN",
      "slug": "btc-updown-5m-1779384300"
    },
    {
      "timestamp": "2026-05-21T17:20:14.411248+00:00",
      "coin": "ETH",
      "direction": "UP",
      "entry_price": 0.63,
      "secs": 14.3,
      "outcome": "WIN",
      "slug": "eth-updown-5m-1779384000"
    },
    {
      "timestamp": "2026-05-21T17:20:12.838647+00:00",
      "coin": "BTC",
      "direction": "UP",
      "entry_price": 0.59,
      "secs": 12.7,
      "outcome": "WIN",
      "slug": "btc-updown-5m-1779384000"
    },
    {
      "timestamp": "2026-05-21T17:00:03.259850+00:00",
      "coin": "BTC",
      "direction": "UP",
      "entry_price": 0.63,
      "secs": 3.2,
      "outcome": "WIN",
      "slug": "btc-updown-5m-1779382800"
    },
    {
      "timestamp": "2026-05-21T16:55:29.537374+00:00",
      "coin": "BTC",
      "direction": "UP",
      "entry_price": 0.62,
      "secs": 29.4,
      "outcome": "WIN",
      "slug": "btc-updown-5m-1779382500"
    },
    {
      "timestamp": "2026-05-21T16:45:06.789568+00:00",
      "coin": "BTC",
      "direction": "UP",
      "entry_price": 0.63,
      "secs": 6.7,
      "outcome": "LOSS",
      "slug": "btc-updown-5m-1779381900"
    },
    {
      "timestamp": "2026-05-21T16:45:01.789349+00:00",
      "coin": "ETH",
      "direction": "UP",
      "entry_price": 0.6,
      "secs": 1.6,
      "outcome": "WIN",
      "slug": "eth-updown-5m-1779381900"
    },
    {
      "timestamp": "2026-05-21T16:30:18.998543+00:00",
      "coin": "BTC",
      "direction": "UP",
      "entry_price": 0.6,
      "secs": 18.6,
      "outcome": "WIN",
      "slug": "btc-updown-5m-1779381000"
    },
    {
      "timestamp": "2026-05-21T16:30:16.814785+00:00",
      "coin": "ETH",
      "direction": "UP",
      "entry_price": 0.59,
      "secs": 16.7,
      "outcome": "WIN",
      "slug": "eth-updown-5m-1779381000"
    },
    {
      "timestamp": "2026-05-21T16:20:15.272658+00:00",
      "coin": "ETH",
      "direction": "UP",
      "entry_price": 0.59,
      "secs": 15.2,
      "outcome": "LOSS",
      "slug": "eth-updown-5m-1779380400"
    },
    {
      "timestamp": "2026-05-21T16:20:09.448827+00:00",
      "coin": "BTC",
      "direction": "UP",
      "entry_price": 0.62,
      "secs": 9.4,
      "outcome": "LOSS",
      "slug": "btc-updown-5m-1779380400"
    },
    {
      "timestamp": "2026-05-21T16:15:15.214945+00:00",
      "coin": "ETH",
      "direction": "UP",
      "entry_price": 0.57,
      "secs": 15.1,
      "outcome": "LOSS",
      "slug": "eth-updown-5m-1779380100"
    }
  ],
  "backtest": {
    "total_trades": 136520,
    "win_rate": 70.5,
    "period": "4 years (Jan 2022 - Mar 2026)",
    "dataset": "Binance BTCUSDT 1m + 5m candles"
  }
}