{
  "updated_at": "2026-05-10T05:44:00.357226+00:00",
  "total_bets": 272,
  "wins": 153,
  "losses": 119,
  "pending": 0,
  "win_rate": 56.2,
  "pnl": -26.15,
  "kelly_pnl": -39.24,
  "current_streak": 1,
  "streak_type": "W",
  "daily": [
    {
      "date": "2026-05-10",
      "bets": 17,
      "wins": 7,
      "losses": 10,
      "wr": 41.2
    },
    {
      "date": "2026-05-09",
      "bets": 97,
      "wins": 54,
      "losses": 43,
      "wr": 55.7
    },
    {
      "date": "2026-05-08",
      "bets": 137,
      "wins": 79,
      "losses": 58,
      "wr": 57.7
    },
    {
      "date": "2026-05-07",
      "bets": 21,
      "wins": 13,
      "losses": 8,
      "wr": 61.9
    }
  ],
  "recent_signals": [
    {
      "timestamp": "2026-05-10T05:10:13.963500+00:00",
      "coin": "ETH",
      "direction": "UP",
      "entry_price": 0.59,
      "secs": 13.9,
      "outcome": "WIN",
      "slug": "eth-updown-5m-1778389800"
    },
    {
      "timestamp": "2026-05-10T04:55:19.166385+00:00",
      "coin": "BTC",
      "direction": "UP",
      "entry_price": 0.64,
      "secs": 19.1,
      "outcome": "LOSS",
      "slug": "btc-updown-5m-1778388900"
    },
    {
      "timestamp": "2026-05-10T04:55:16.227831+00:00",
      "coin": "ETH",
      "direction": "UP",
      "entry_price": 0.57,
      "secs": 16.1,
      "outcome": "LOSS",
      "slug": "eth-updown-5m-1778388900"
    },
    {
      "timestamp": "2026-05-10T04:35:18.834196+00:00",
      "coin": "ETH",
      "direction": "UP",
      "entry_price": 0.64,
      "secs": 18.8,
      "outcome": "WIN",
      "slug": "eth-updown-5m-1778387700"
    },
    {
      "timestamp": "2026-05-10T04:00:15.074095+00:00",
      "coin": "ETH",
      "direction": "UP",
      "entry_price": 0.62,
      "secs": 15.0,
      "outcome": "LOSS",
      "slug": "eth-updown-5m-1778385600"
    },
    {
      "timestamp": "2026-05-10T03:50:23.436659+00:00",
      "coin": "BTC",
      "direction": "UP",
      "entry_price": 0.57,
      "secs": 23.4,
      "outcome": "LOSS",
      "slug": "btc-updown-5m-1778385000"
    },
    {
      "timestamp": "2026-05-10T03:45:11.846905+00:00",
      "coin": "ETH",
      "direction": "UP",
      "entry_price": 0.64,
      "secs": 11.8,
      "outcome": "LOSS",
      "slug": "eth-updown-5m-1778384700"
    },
    {
      "timestamp": "2026-05-10T03:05:17.186706+00:00",
      "coin": "BTC",
      "direction": "UP",
      "entry_price": 0.57,
      "secs": 17.1,
      "outcome": "LOSS",
      "slug": "btc-updown-5m-1778382300"
    },
    {
      "timestamp": "2026-05-10T02:35:19.135546+00:00",
      "coin": "ETH",
      "direction": "UP",
      "entry_price": 0.61,
      "secs": 19.1,
      "outcome": "WIN",
      "slug": "eth-updown-5m-1778380500"
    },
    {
      "timestamp": "2026-05-10T01:40:17.620820+00:00",
      "coin": "ETH",
      "direction": "UP",
      "entry_price": 0.58,
      "secs": 17.6,
      "outcome": "WIN",
      "slug": "eth-updown-5m-1778377200"
    },
    {
      "timestamp": "2026-05-10T01:40:13.945647+00:00",
      "coin": "BTC",
      "direction": "UP",
      "entry_price": 0.64,
      "secs": 13.9,
      "outcome": "WIN",
      "slug": "btc-updown-5m-1778377200"
    },
    {
      "timestamp": "2026-05-10T01:35:09.937461+00:00",
      "coin": "ETH",
      "direction": "UP",
      "entry_price": 0.62,
      "secs": 9.9,
      "outcome": "LOSS",
      "slug": "eth-updown-5m-1778376900"
    },
    {
      "timestamp": "2026-05-10T01:05:08.217635+00:00",
      "coin": "ETH",
      "direction": "UP",
      "entry_price": 0.58,
      "secs": 8.1,
      "outcome": "LOSS",
      "slug": "eth-updown-5m-1778375100"
    },
    {
      "timestamp": "2026-05-10T00:55:14.226971+00:00",
      "coin": "ETH",
      "direction": "UP",
      "entry_price": 0.59,
      "secs": 14.1,
      "outcome": "LOSS",
      "slug": "eth-updown-5m-1778374500"
    },
    {
      "timestamp": "2026-05-10T00:35:18.213277+00:00",
      "coin": "ETH",
      "direction": "UP",
      "entry_price": 0.59,
      "secs": 18.1,
      "outcome": "LOSS",
      "slug": "eth-updown-5m-1778373300"
    },
    {
      "timestamp": "2026-05-10T00:10:10.103230+00:00",
      "coin": "BTC",
      "direction": "UP",
      "entry_price": 0.6,
      "secs": 10.0,
      "outcome": "WIN",
      "slug": "btc-updown-5m-1778371800"
    },
    {
      "timestamp": "2026-05-10T00:05:13.815652+00:00",
      "coin": "BTC",
      "direction": "UP",
      "entry_price": 0.6,
      "secs": 13.7,
      "outcome": "WIN",
      "slug": "btc-updown-5m-1778371500"
    },
    {
      "timestamp": "2026-05-09T23:45:07.347760+00:00",
      "coin": "BTC",
      "direction": "UP",
      "entry_price": 0.62,
      "secs": 7.2,
      "outcome": "WIN",
      "slug": "btc-updown-5m-1778370300"
    },
    {
      "timestamp": "2026-05-09T23:35:12.295774+00:00",
      "coin": "BTC",
      "direction": "UP",
      "entry_price": 0.57,
      "secs": 12.2,
      "outcome": "LOSS",
      "slug": "btc-updown-5m-1778369700"
    },
    {
      "timestamp": "2026-05-09T23:20:20.054032+00:00",
      "coin": "BTC",
      "direction": "UP",
      "entry_price": 0.58,
      "secs": 20.0,
      "outcome": "LOSS",
      "slug": "btc-updown-5m-1778368800"
    }
  ],
  "backtest": {
    "total_trades": 136520,
    "win_rate": 70.5,
    "period": "4 years (Jan 2022 - Mar 2026)",
    "dataset": "Binance BTCUSDT 1m + 5m candles"
  }
}