{
  "updated_at": "2026-04-17T06:02:10.656759+00:00",
  "total_bets": 117,
  "wins": 53,
  "losses": 17,
  "pending": 47,
  "win_rate": 75.7,
  "pnl": -1.18,
  "current_streak": 2,
  "streak_type": "L",
  "daily": [
    {
      "date": "2026-04-17",
      "bets": 2,
      "wins": 0,
      "losses": 2,
      "wr": 0.0
    },
    {
      "date": "2026-04-08",
      "bets": 44,
      "wins": 32,
      "losses": 12,
      "wr": 72.7
    },
    {
      "date": "2026-04-05",
      "bets": 4,
      "wins": 3,
      "losses": 1,
      "wr": 75.0
    },
    {
      "date": "2026-04-04",
      "bets": 20,
      "wins": 18,
      "losses": 2,
      "wr": 90.0
    }
  ],
  "recent_signals": [
    {
      "timestamp": "2026-04-17T05:50:27.934942+00:00",
      "coin": "BTC",
      "direction": "DOWN",
      "entry_price": 0.57,
      "secs": 27.9,
      "outcome": "LOSS",
      "slug": "btc-updown-5m-1776405000"
    },
    {
      "timestamp": "2026-04-17T05:45:11.782689+00:00",
      "coin": "BTC",
      "direction": "DOWN",
      "entry_price": 0.57,
      "secs": 11.8,
      "outcome": "LOSS",
      "slug": "btc-updown-5m-1776404700"
    },
    {
      "timestamp": "2026-04-15T21:19:59.039411+00:00",
      "coin": "NEAREXPIRYSTRATEGY",
      "direction": null,
      "entry_price": null,
      "secs": null,
      "outcome": "PENDING",
      "slug": null
    },
    {
      "timestamp": "2026-04-15T21:19:59.032569+00:00",
      "coin": "LLMGENERALSTRATEGY",
      "direction": null,
      "entry_price": null,
      "secs": null,
      "outcome": "PENDING",
      "slug": null
    },
    {
      "timestamp": "2026-04-08T19:24:54.292087+00:00",
      "coin": "NEAREXPIRYSTRATEGY",
      "direction": null,
      "entry_price": null,
      "secs": null,
      "outcome": "PENDING",
      "slug": null
    },
    {
      "timestamp": "2026-04-08T19:24:54.270364+00:00",
      "coin": "LLMGENERALSTRATEGY",
      "direction": null,
      "entry_price": null,
      "secs": null,
      "outcome": "PENDING",
      "slug": null
    },
    {
      "timestamp": "2026-04-08T19:23:41.567238+00:00",
      "coin": "NEAREXPIRYSTRATEGY",
      "direction": null,
      "entry_price": null,
      "secs": null,
      "outcome": "PENDING",
      "slug": null
    },
    {
      "timestamp": "2026-04-08T19:23:41.533509+00:00",
      "coin": "LLMGENERALSTRATEGY",
      "direction": null,
      "entry_price": null,
      "secs": null,
      "outcome": "PENDING",
      "slug": null
    },
    {
      "timestamp": "2026-04-08T19:23:07.268855+00:00",
      "coin": "NEAREXPIRYSTRATEGY",
      "direction": null,
      "entry_price": null,
      "secs": null,
      "outcome": "PENDING",
      "slug": null
    },
    {
      "timestamp": "2026-04-08T19:23:07.256987+00:00",
      "coin": "LLMGENERALSTRATEGY",
      "direction": null,
      "entry_price": null,
      "secs": null,
      "outcome": "PENDING",
      "slug": null
    },
    {
      "timestamp": "2026-04-08T19:21:25.423011+00:00",
      "coin": "NEAREXPIRYSTRATEGY",
      "direction": null,
      "entry_price": null,
      "secs": null,
      "outcome": "PENDING",
      "slug": null
    },
    {
      "timestamp": "2026-04-08T19:21:25.368597+00:00",
      "coin": "LLMGENERALSTRATEGY",
      "direction": null,
      "entry_price": null,
      "secs": null,
      "outcome": "PENDING",
      "slug": null
    },
    {
      "timestamp": "2026-04-08T17:52:28.431057+00:00",
      "coin": "BTC",
      "direction": "DOWN",
      "entry_price": null,
      "secs": null,
      "outcome": "WIN",
      "slug": "btc-updown-5m-1775670600"
    },
    {
      "timestamp": "2026-04-08T17:48:44.022040+00:00",
      "coin": "ETH",
      "direction": "DOWN",
      "entry_price": null,
      "secs": null,
      "outcome": "WIN",
      "slug": "eth-updown-5m-1775670300"
    },
    {
      "timestamp": "2026-04-08T17:43:34.807207+00:00",
      "coin": "ETH",
      "direction": "DOWN",
      "entry_price": null,
      "secs": null,
      "outcome": "WIN",
      "slug": "eth-updown-5m-1775670000"
    },
    {
      "timestamp": "2026-04-08T17:43:28.714773+00:00",
      "coin": "BTC",
      "direction": "DOWN",
      "entry_price": null,
      "secs": null,
      "outcome": "LOSS",
      "slug": "btc-updown-5m-1775670000"
    },
    {
      "timestamp": "2026-04-08T17:35:34.767224+00:00",
      "coin": "BTC",
      "direction": "DOWN",
      "entry_price": null,
      "secs": null,
      "outcome": "LOSS",
      "slug": "btc-updown-5m-1775669700"
    },
    {
      "timestamp": "2026-04-08T17:32:29.762852+00:00",
      "coin": "ETH",
      "direction": "UP",
      "entry_price": null,
      "secs": null,
      "outcome": "WIN",
      "slug": "eth-updown-5m-1775669400"
    },
    {
      "timestamp": "2026-04-08T17:30:24.801258+00:00",
      "coin": "BTC",
      "direction": "DOWN",
      "entry_price": null,
      "secs": null,
      "outcome": "WIN",
      "slug": "btc-updown-5m-1775669400"
    },
    {
      "timestamp": "2026-04-08T17:28:29.343417+00:00",
      "coin": "BTC",
      "direction": "DOWN",
      "entry_price": null,
      "secs": null,
      "outcome": "LOSS",
      "slug": "btc-updown-5m-1775669100"
    }
  ],
  "backtest": {
    "total_trades": 136520,
    "win_rate": 70.5,
    "period": "4 years (Jan 2022 - Mar 2026)",
    "dataset": "Binance BTCUSDT 1m + 5m candles"
  }
}