{
  "updated_at": "2026-04-25T05:03:55.250893+00:00",
  "total_bets": 570,
  "wins": 319,
  "losses": 251,
  "pending": 0,
  "win_rate": 56.0,
  "pnl": -40.93,
  "kelly_pnl": -60.15,
  "current_streak": 1,
  "streak_type": "L",
  "daily": [
    {
      "date": "2026-04-25",
      "bets": 12,
      "wins": 8,
      "losses": 4,
      "wr": 66.7
    },
    {
      "date": "2026-04-24",
      "bets": 116,
      "wins": 66,
      "losses": 50,
      "wr": 56.9
    },
    {
      "date": "2026-04-23",
      "bets": 113,
      "wins": 65,
      "losses": 48,
      "wr": 57.5
    },
    {
      "date": "2026-04-22",
      "bets": 142,
      "wins": 76,
      "losses": 66,
      "wr": 53.5
    },
    {
      "date": "2026-04-21",
      "bets": 149,
      "wins": 85,
      "losses": 64,
      "wr": 57.0
    },
    {
      "date": "2026-04-20",
      "bets": 38,
      "wins": 19,
      "losses": 19,
      "wr": 50.0
    }
  ],
  "recent_signals": [
    {
      "timestamp": "2026-04-25T04:40:05.883321+00:00",
      "coin": "BTC",
      "direction": "DOWN",
      "entry_price": 0.59,
      "secs": 5.7,
      "outcome": "LOSS",
      "slug": "btc-updown-5m-1777092000"
    },
    {
      "timestamp": "2026-04-25T04:30:13.744914+00:00",
      "coin": "BTC",
      "direction": "DOWN",
      "entry_price": 0.59,
      "secs": 13.5,
      "outcome": "WIN",
      "slug": "btc-updown-5m-1777091400"
    },
    {
      "timestamp": "2026-04-25T03:35:09.688592+00:00",
      "coin": "ETH",
      "direction": "DOWN",
      "entry_price": 0.58,
      "secs": 9.5,
      "outcome": "WIN",
      "slug": "eth-updown-5m-1777088100"
    },
    {
      "timestamp": "2026-04-25T02:40:29.249189+00:00",
      "coin": "BTC",
      "direction": "DOWN",
      "entry_price": 0.58,
      "secs": 29.0,
      "outcome": "WIN",
      "slug": "btc-updown-5m-1777084800"
    },
    {
      "timestamp": "2026-04-25T02:30:23.395859+00:00",
      "coin": "BTC",
      "direction": "DOWN",
      "entry_price": 0.58,
      "secs": 23.1,
      "outcome": "WIN",
      "slug": "btc-updown-5m-1777084200"
    },
    {
      "timestamp": "2026-04-25T02:20:09.566323+00:00",
      "coin": "ETH",
      "direction": "DOWN",
      "entry_price": 0.59,
      "secs": 9.3,
      "outcome": "LOSS",
      "slug": "eth-updown-5m-1777083600"
    },
    {
      "timestamp": "2026-04-25T02:10:14.329245+00:00",
      "coin": "ETH",
      "direction": "DOWN",
      "entry_price": 0.58,
      "secs": 13.8,
      "outcome": "LOSS",
      "slug": "eth-updown-5m-1777083000"
    },
    {
      "timestamp": "2026-04-25T01:50:15.551270+00:00",
      "coin": "BTC",
      "direction": "DOWN",
      "entry_price": 0.59,
      "secs": 15.3,
      "outcome": "WIN",
      "slug": "btc-updown-5m-1777081800"
    },
    {
      "timestamp": "2026-04-25T01:50:06.140343+00:00",
      "coin": "ETH",
      "direction": "DOWN",
      "entry_price": 0.59,
      "secs": 5.8,
      "outcome": "WIN",
      "slug": "eth-updown-5m-1777081800"
    },
    {
      "timestamp": "2026-04-25T01:25:27.757722+00:00",
      "coin": "BTC",
      "direction": "DOWN",
      "entry_price": 0.59,
      "secs": 27.5,
      "outcome": "WIN",
      "slug": "btc-updown-5m-1777080300"
    },
    {
      "timestamp": "2026-04-25T01:20:03.586011+00:00",
      "coin": "BTC",
      "direction": "DOWN",
      "entry_price": 0.59,
      "secs": 3.4,
      "outcome": "WIN",
      "slug": "btc-updown-5m-1777080000"
    },
    {
      "timestamp": "2026-04-25T01:10:07.566712+00:00",
      "coin": "ETH",
      "direction": "DOWN",
      "entry_price": 0.58,
      "secs": 6.3,
      "outcome": "LOSS",
      "slug": "eth-updown-5m-1777079400"
    },
    {
      "timestamp": "2026-04-24T23:35:08.509244+00:00",
      "coin": "BTC",
      "direction": "DOWN",
      "entry_price": 0.59,
      "secs": 8.2,
      "outcome": "WIN",
      "slug": "btc-updown-5m-1777073700"
    },
    {
      "timestamp": "2026-04-24T23:30:30.356953+00:00",
      "coin": "BTC",
      "direction": "DOWN",
      "entry_price": 0.59,
      "secs": 30.1,
      "outcome": "LOSS",
      "slug": "btc-updown-5m-1777073400"
    },
    {
      "timestamp": "2026-04-24T23:15:15.947708+00:00",
      "coin": "BTC",
      "direction": "DOWN",
      "entry_price": 0.59,
      "secs": 15.7,
      "outcome": "LOSS",
      "slug": "btc-updown-5m-1777072500"
    },
    {
      "timestamp": "2026-04-24T21:30:05.024259+00:00",
      "coin": "ETH",
      "direction": "DOWN",
      "entry_price": 0.59,
      "secs": 4.8,
      "outcome": "LOSS",
      "slug": "eth-updown-5m-1777066200"
    },
    {
      "timestamp": "2026-04-24T21:10:14.025164+00:00",
      "coin": "BTC",
      "direction": "DOWN",
      "entry_price": 0.58,
      "secs": 13.8,
      "outcome": "WIN",
      "slug": "btc-updown-5m-1777065000"
    },
    {
      "timestamp": "2026-04-24T21:05:02.397775+00:00",
      "coin": "BTC",
      "direction": "DOWN",
      "entry_price": 0.59,
      "secs": 2.2,
      "outcome": "WIN",
      "slug": "btc-updown-5m-1777064700"
    },
    {
      "timestamp": "2026-04-24T20:50:07.916692+00:00",
      "coin": "ETH",
      "direction": "DOWN",
      "entry_price": 0.58,
      "secs": 7.7,
      "outcome": "LOSS",
      "slug": "eth-updown-5m-1777063800"
    },
    {
      "timestamp": "2026-04-24T20:50:07.359929+00:00",
      "coin": "BTC",
      "direction": "DOWN",
      "entry_price": 0.59,
      "secs": 6.9,
      "outcome": "LOSS",
      "slug": "btc-updown-5m-1777063800"
    }
  ],
  "backtest": {
    "total_trades": 136520,
    "win_rate": 70.5,
    "period": "4 years (Jan 2022 - Mar 2026)",
    "dataset": "Binance BTCUSDT 1m + 5m candles"
  }
}